setup.py
DecoCache.egg-info/PKG-INFO
DecoCache.egg-info/SOURCES.txt
DecoCache.egg-info/dependency_links.txt
DecoCache.egg-info/top_level.txt
decocache/__init__.py
decocache/cache.py
decocache/test_cache.py