Metadata-Version: 1.1
Name: DecoCache
Version: 1.0.0
Summary: A function-caching decorator class.
Home-page: http://eyeballtrees.com/decocache
Author: Stephen Malone AKA Eyeball Trees
Author-email: mail@eyeballtrees.com
License: WTFPL
Keywords: decorator cache caching
Platform: UNKNOWN
Classifier: Development Status :: 5 - Production/Stable
Classifier: Programming Language :: Python :: 3.3
Classifier: Topic :: Software Development :: Libraries
